{"cameraMode":{"drawMode":0,"name":"Shaded","section":"Shading Mode"},"sceneLighting":true,"audioPlay":false,"sceneViewState":{"m_AlwaysRefresh":false,"showFog":true,"showSkybox":true,"showFlares":true,"showImageEffects":true,"showParticleSystems":true,"showVisualEffectGraphs":true,"m_FxEnabled":true},"in2DMode":false,"pivot":{"x":-16.18424415588379,"y":7.544205188751221,"z":-9.849516868591309},"rotation":{"x":-0.11344748735427857,"y":-0.24302639067173005,"z":0.02882159687578678,"w":-0.9630299210548401},"size":6.062159538269043,"orthographic":false}